MANIFEST.in
README
requirements.txt
setup.py
ajenti.plugin.core.egg-info/PKG-INFO
ajenti.plugin.core.egg-info/SOURCES.txt
ajenti.plugin.core.egg-info/dependency_links.txt
ajenti.plugin.core.egg-info/requires.txt
ajenti.plugin.core.egg-info/top_level.txt
ajenti_plugin_core/__init__.py
ajenti_plugin_core/bower.json
ajenti_plugin_core/main.py
ajenti_plugin_core/plugin.yml
ajenti_plugin_core/requirements.txt
ajenti_plugin_core/api/__init__.py
ajenti_plugin_core/api/navbox.py
ajenti_plugin_core/api/push.py
ajenti_plugin_core/api/sidebar.py
ajenti_plugin_core/api/tasks.py
ajenti_plugin_core/content/pages/index.html
ajenti_plugin_core/locale/app.pot
ajenti_plugin_core/locale/af/LC_MESSAGES/app.js
ajenti_plugin_core/locale/af/LC_MESSAGES/app.po
ajenti_plugin_core/locale/ar/LC_MESSAGES/app.js
ajenti_plugin_core/locale/ar/LC_MESSAGES/app.po
ajenti_plugin_core/locale/be/LC_MESSAGES/app.js
ajenti_plugin_core/locale/be/LC_MESSAGES/app.po
ajenti_plugin_core/locale/bg/LC_MESSAGES/app.js
ajenti_plugin_core/locale/bg/LC_MESSAGES/app.po
ajenti_plugin_core/locale/bn/LC_MESSAGES/app.js
ajenti_plugin_core/locale/bn/LC_MESSAGES/app.po
ajenti_plugin_core/locale/ca/LC_MESSAGES/app.js
ajenti_plugin_core/locale/ca/LC_MESSAGES/app.po
ajenti_plugin_core/locale/cs/LC_MESSAGES/app.js
ajenti_plugin_core/locale/cs/LC_MESSAGES/app.po
ajenti_plugin_core/locale/da/LC_MESSAGES/app.js
ajenti_plugin_core/locale/da/LC_MESSAGES/app.po
ajenti_plugin_core/locale/de/LC_MESSAGES/app.js
ajenti_plugin_core/locale/de/LC_MESSAGES/app.po
ajenti_plugin_core/locale/el/LC_MESSAGES/app.js
ajenti_plugin_core/locale/el/LC_MESSAGES/app.po
ajenti_plugin_core/locale/en/LC_MESSAGES/app.po
ajenti_plugin_core/locale/eo/LC_MESSAGES/app.js
ajenti_plugin_core/locale/eo/LC_MESSAGES/app.po
ajenti_plugin_core/locale/es-ES/LC_MESSAGES/app.js
ajenti_plugin_core/locale/es-ES/LC_MESSAGES/app.po
ajenti_plugin_core/locale/et/LC_MESSAGES/app.js
ajenti_plugin_core/locale/et/LC_MESSAGES/app.po
ajenti_plugin_core/locale/fa/LC_MESSAGES/app.js
ajenti_plugin_core/locale/fa/LC_MESSAGES/app.po
ajenti_plugin_core/locale/fi/LC_MESSAGES/app.js
ajenti_plugin_core/locale/fi/LC_MESSAGES/app.po
ajenti_plugin_core/locale/fr/LC_MESSAGES/app.js
