Metadata-Version: 1.0
Name: ajenti.plugin.core
Version: 0.91
Summary: Core
Home-page: http://ajenti.org
Author: Ajenti project
Author-email: e@ajenti.org
License: UNKNOWN
Platform: UNKNOWN
